Metadata-Version: 2.1
Name: image-quotes
Version: 0.0.1
Summary: A package to get inspirational images for your #MondayMotivation
Home-page: https://github.com/BruceCodesGithub/img-quotes
Author: Bruce
Author-email: brucealt69@gmail.com
License: UNKNOWN
Platform: UNKNOWN
Classifier: Programming Language :: Python :: 3
Classifier: License :: OSI Approved :: MIT License
Classifier: Operating System :: OS Independent
Requires-Python: >=3.6
License-File: LICENCE.txt
